{
	"configurations" : 
	[
		{
			"directories" : 
			[
				{
					"build" : ".",
					"jsonFile" : "directory-.-Debug-d0094a50bb2071803777.json",
					"minimumCMakeVersion" : 
					{
						"string" : "3.30"
					},
					"projectIndex" : 0,
					"source" : ".",
					"targetIndexes" : 
					[
						0
					]
				}
			],
			"name" : "Debug",
			"projects" : 
			[
				{
					"directoryIndexes" : 
					[
						0
					],
					"name" : "cube_rotation",
					"targetIndexes" : 
					[
						0
					]
				}
			],
			"targets" : 
			[
				{
					"directoryIndex" : 0,
					"id" : "cube_rotation::@6890427a1f51a3e7e1df",
					"jsonFile" : "target-cube_rotation-Debug-e0ef300269cabf3f65d8.json",
					"name" : "cube_rotation",
					"projectIndex" : 0
				}
			]
		}
	],
	"kind" : "codemodel",
	"paths" : 
	{
		"build" : "C:/Users/akbul/OneDrive/Masa\u00fcst\u00fc/workspace/cube_rotation/cmake-build-debug",
		"source" : "C:/Users/akbul/OneDrive/Masa\u00fcst\u00fc/workspace/cube_rotation"
	},
	"version" : 
	{
		"major" : 2,
		"minor" : 7
	}
}
